[{"ItemID":2000,"EntityID":1800,"StateTime1":600,"StateTime2":1200,"DestroyAddItem":2500,"Count":5,"ID":1},{"ItemID":2001,"EntityID":1801,"StateTime1":800,"StateTime2":1500,"DestroyAddItem":2501,"Count":5,"ID":2},{"ItemID":2002,"EntityID":1802,"StateTime1":1000,"StateTime2":2000,"DestroyAddItem":2502,"Count":5,"ID":3},{"ItemID":2003,"EntityID":1803,"StateTime1":300,"StateTime2":600,"DestroyAddItem":2503,"Count":8,"ID":4},{"ItemID":2004,"EntityID":1804,"StateTime1":600,"StateTime2":1200,"DestroyAddItem":2504,"Count":3,"ID":5}]